tokenlearn/__init__.py
tokenlearn/featurize.py
tokenlearn/pretrain.py
tokenlearn/train.py
tokenlearn/utils.py
tokenlearn/version.py
tokenlearn-0.2.1.dist-info/licenses/LICENSE
tokenlearn-0.2.1.dist-info/METADATA
tokenlearn-0.2.1.dist-info/WHEEL
tokenlearn-0.2.1.dist-info/top_level.txt
tokenlearn-0.2.1.dist-info/RECORD
