Metadata-Version: 2.4
Name: tokenlearn
Version: 0.2.1
Summary: Pre-train Static Embedders
Author-email: Thomas van Dongen <thomas123@live.nl>, Stéphan Tulkens <stephantul@gmail.com>
License: MIT License
Project-URL: Homepage, https://github.com/MinishLab
Project-URL: Bug Reports, https://github.com/MinishLab/tokenlearn/issues
Project-URL: Source, https://github.com/MinishLab/tokenlearn
Classifier: Development Status :: 4 - Beta
Classifier: Intended Audience :: Developers
Classifier: Intended Audience :: Science/Research
Classifier: Topic :: Scientific/Engineering :: Artificial Intelligence
Classifier: Topic :: Software Development :: Libraries
Classifier: License :: OSI Approved :: MIT License
Classifier: Programming Language :: Python :: 3 :: Only
Classifier: Programming Language :: Python :: 3.9
Classifier: Programming Language :: Python :: 3.10
Classifier: Programming Language :: Python :: 3.11
Classifier: Programming Language :: Python :: 3.12
Classifier: Natural Language :: English
Requires-Python: >=3.9
License-File: LICENSE
Requires-Dist: model2vec[distill]>=0.5.0
Requires-Dist: sentence-transformers
Requires-Dist: torch
Requires-Dist: datasets
Requires-Dist: more-itertools>=10.5.0
Provides-Extra: dev
Requires-Dist: black; extra == "dev"
Requires-Dist: ipython; extra == "dev"
Requires-Dist: mypy; extra == "dev"
Requires-Dist: pre-commit; extra == "dev"
Requires-Dist: pytest; extra == "dev"
Requires-Dist: pytest-coverage; extra == "dev"
Requires-Dist: ruff; extra == "dev"
Dynamic: license-file
